xram16x1.v
/*
 * Copyright (c) 1999 Stephen Williams (steve@icarus.com)
 *
 *    This source code is free software; you can redistribute it
 *    and/or modify it in source code form under the terms of the GNU
 *    General Public License as published by the Free Software
 *    Foundation; either version 2 of the License, or (at your option)
 *    any later version.
 *
 *    This program is distributed in the hope that it will be useful,
 *    but WITHOUT ANY WARRANTY; without even the implied warranty of
 *    MERCHANTABILITY or FITNESS FOR A PARTICULAR PURPOSE.  See the
 *    GNU General Public License for more details.
 *
 *    You should have received a copy of the GNU General Public License
 *    along with this program; if not, write to the Free Software
 *    Foundation, Inc., 51 Franklin Street, Fifth Floor, Boston, MA 02110-1301, USA.
 */

 /*
  *  This example program simulates a 16x1 ram, and is used as an
  *  example for using VCD output and waveform viewers.
  *
  *  Like any other Verilog simulation, compile this program with the
  *  command:
  *
  *      iverilog show_vcd.vl
  *
  *  This will generate the show_vcd command in the current directory.
  *  When you run the command, you will see the output from all the
  *  calls to $display, but also there will be a dump file ``show_vcd.vcd''.
  *  The name of this file is set by the statement:
  *
  *      $dumpfile("show_vcd.vcd");
  *
  *  in the main module. The output file uses the standard VCD file format
  *  so can be viewed using off-the-shelf waveform viewers. The remaining
  *  steps describe how to use GTKWave to view the file. If you are using
  *  a different viewer, see the documentation for that tool.
  *
  *  To view the output generated by running show_vcd, start the GTKWave
  *  viewer with the command:
  *
  *      gtkwave show_vcd.vcd
  *
  *  The GTKWave program will display its main window, and show in a small
  *  status box (upper left corner) that it succeeded in loading the dump
  *  file. However, there are no waveforms displayed yet. Select signals to
  *  add to the waveform display using the menu selection:
  *
  *      "Search --> Signal Search Tree"
  *
  *  This will bring up a dialog box that shows in directory tree format
  *  the signals of the program. Select the signals you wish to view, and
  *  click one of the buttons on the bottom of the dialog box to display
  *  the selected signals in the waveform window. Click "Exit" on the box
  *  to get rid of it.
  *
  *  The magic that makes all this work is contained in the $dumpfile and
  *  $dumpvars system tasks. The $dumpfile task tells the simulation where
  *  to write the VCD output. This task must be called once before the
  *  $dumpvars task is called.
  *
  *  The $dumpvars task tells the simulation what variables to write to
  *  the VCD output. The first parameter is how far to descend while
  *  scanning a scope, and the remaining parameters are signals or scope
  *  names to include in the dump. If a scope name is given, all the
  *  signals within the scope are dumped. If a wire or register name is
  *  given, that signal is included.
  */

 module ram16x1 (out, data, index, assign_flag, wclk);
     output out;
     input data;
     input [3:0] index;
     input assign_flag;
     input wclk;

     reg mem[15:0];

     assign out = mem[index];
     always @(posedge wclk) if (assign_flag) mem[index] = data;

 endmodule /* ram16x1 */

module main;
    wire out;
    reg data;
    reg [3:0] index;
    reg assign_flag, wclk;

    ram16x1 r1 (out, data, index, assign_flag, wclk);

    initial begin
    $dumpfile("show_vcd.vcd");
    $dumpvars(1, main.r1);
    wclk = 0;
    assign_flag = 1;
    for (index = 0 ; index < 4'hf ;  index = index + 1) begin
        data = index[0];
        #1 wclk = 1; //the data is written to ram on positve edge
        #1 wclk = 0;
        $display("r1[%x] == %b", index, out);
    end

    for (index = 0 ; index < 4'hf ;  index = index + 1)
        #1 if (out !== index[0]) begin
            $display("FAILED -- mem[%h] !== %b", index, index[0]);
            $finish;
        end

        $display("PASSED");
    end
endmodule /* main */

show_vcd.vcd
$date
	Sun Mar 29 18:35:39 2020
$end
$version
	Icarus Verilog
$end
$timescale
	1s
$end
$scope module main $end
$scope module r1 $end
$var wire 1 ! assign_flag $end
$var wire 1 " data $end
$var wire 4 # index [3:0] $end
$var wire 1 $ out $end
$var wire 1 % wclk $end
$upscope $end
$upscope $end
$enddefinitions $end
#0
$dumpvars
0%
x$
b0 #
0"
1!
$end
#1
0$
1%
#2
1"
x$
b1 #
0%
#3
1$
1%
#4
0"
x$
b10 #
0%
#5
0$
1%
#6
1"
x$
b11 #
0%
#7
1$
1%
#8
0"
x$
b100 #
0%
#9
0$
1%
#10
1"
x$
b101 #
0%
#11
1$
1%
#12
0"
x$
b110 #
0%
#13
0$
1%
#14
1"
x$
b111 #
0%
#15
1$
1%
#16
0"
x$
b1000 #
0%
#17
0$
1%
#18
1"
x$
b1001 #
0%
#19
1$
1%
#20
0"
x$
b1010 #
0%
#21
0$
1%
#22
1"
x$
b1011 #
0%
#23
1$
1%
#24
0"
x$
b1100 #
0%
#25
0$
1%
#26
1"
x$
b1101 #
0%
#27
1$
1%
#28
0"
x$
b1110 #
0%
#29
0$
1%
#30
0$
b0 #
0%
#31
1$
b1 #
#32
0$
b10 #
#33
1$
b11 #
#34
0$
b100 #
#35
1$
b101 #
#36
0$
b110 #
#37
1$
b111 #
#38
0$
b1000 #
#39
1$
b1001 #
#40
0$
b1010 #
#41
1$
b1011 #
#42
0$
b1100 #
#43
1$
b1101 #
#44
0$
b1110 #
#45
x$
b1111 #
